pysabertooth/PySabertooth.py
pysabertooth/__init__.py
pysabertooth-0.4.0.dist-info/LICENSE
pysabertooth-0.4.0.dist-info/WHEEL
pysabertooth-0.4.0.dist-info/METADATA
pysabertooth-0.4.0.dist-info/RECORD
